core/migrations/__init__.py
django_core_waili-0.1.4.dist-info/DESCRIPTION.rst
django_core_waili-0.1.4.dist-info/METADATA
django_core_waili-0.1.4.dist-info/RECORD
django_core_waili-0.1.4.dist-info/WHEEL
django_core_waili-0.1.4.dist-info/metadata.json
django_core_waili-0.1.4.dist-info/top_level.txt
