Metadata-Version: 2.0
Name: django-core-waili
Version: 0.1.4
Summary: Django tools
Home-page: https://github.com/linxuedong/django-core-waili
Author: linxuedong
Author-email: xuedonglin1994@gmail.com
License: UNKNOWN
Keywords: django tools
Platform: UNKNOWN
Classifier: Development Status :: 3 - Alpha
Classifier: Intended Audience :: Developers
Classifier: Topic :: Software Development :: Build Tools
Classifier: License :: OSI Approved :: MIT License
Classifier: Programming Language :: Python :: 3.6
Classifier: Framework :: Django
